img2epub/__init__.py
img2epub/command.py
img2epub/functions.py
img2epub/data/book.opf.template
img2epub/data/chap1.xhtml.template
img2epub/data/container.xml
img2epub/data/nav.xhtml
img2epub-0.3.0.dist-info/LICENSE.txt
img2epub-0.3.0.dist-info/METADATA
img2epub-0.3.0.dist-info/WHEEL
img2epub-0.3.0.dist-info/entry_points.txt
img2epub-0.3.0.dist-info/top_level.txt
img2epub-0.3.0.dist-info/RECORD
